[
    {
        "uri": "https://youtu.be/SBpWWu32YSg",
        "title": "ЛУЧШИЕ ПРИКОЛЫ АВГУСТ 2017 | Чумовая Подборка Приколов #176",
        "tags": [
            "прикол", "август", "2017"
        ]
    },
    {
        "uri": "https://youtu.be/vct4pM4Bk70",
        "title": "How to design a logo with golden Ratio | Adobe Illustrator Tutorial",
        "tags": [
            "хобби", "tutorial", "adobe ilustrator"
        ]
    },
    {
        "uri": "https://youtu.be/IfXe1RYcz24",
        "title": "Узнай какой ты программист! — Суровый веб #138",
        "tags": [
            "образование", "веб", "подкаст"
        ]
    }
]